# Kotlin给任意类增加方法，在字节码层面是如何实现的？

Kotlin 的「给任意类增加方法」本质是 **扩展函数（Extension Functions）** 语法糖，其核心原理是：**不修改目标类的字节码，而是通过编译器将扩展函数编译为静态工具方法**，目标类完全无感知。下面从字节码层面详细拆解实现逻辑：


### 一、核心结论
Kotlin 扩展函数**不会修改目标类（被扩展的类）的字节码结构**（目标类的字段、方法列表完全不变），而是将扩展函数编译为：
- 顶层扩展函数 → 对应 `.kt` 文件生成的 `XXXKt` 工具类中的**静态方法**；
- 类内部的扩展函数 → 所在类的**静态方法**（或非静态方法，取决于是否是 `inner` 扩展）；
- 扩展函数的「接收者（this）」会被编译为静态方法的**第一个参数**。


### 二、具体字节码实现细节（结合示例）
我们用一个简单示例拆解编译过程，步骤：Kotlin 源码 → 反编译 Java 代码 → 字节码指令。

#### 示例 1：顶层扩展函数（最常见场景）
##### 1. Kotlin 源码（`StringExtensions.kt`）
给 Java 的 `String` 类扩展一个 `hello()` 方法：
```kotlin
// StringExtensions.kt
fun String.hello(prefix: String): String {
    return "$prefix, ${this.length} 个字符" // this 指代 String 接收者
}

// 调用扩展函数
fun main() {
    val str = "Kotlin"
    println(str.hello("Hi")) // 输出：Hi, 6 个字符
}
```

##### 2. 编译后的 Java 等效代码（反编译结果）
Kotlin 编译器会将 `StringExtensions.kt` 编译为 `StringExtensionsKt` 工具类（顶层文件默认生成 `XXXKt` 类），扩展函数 `hello` 被编译为**静态方法**，接收者 `String` 作为第一个参数：
```java
// 反编译后的 StringExtensionsKt.class
public final class StringExtensionsKt {
    // 扩展函数 → 静态方法：第一个参数是接收者 String，后续是原参数
    public static final String hello(String $this$hello, String prefix) {
        Intrinsics.checkNotNullParameter($this$hello, "$this$hello"); // 非空检查
        Intrinsics.checkNotNullParameter(prefix, "prefix");
        return prefix + ", " + $this$hello.length() + " 个字符";
    }

    public static final void main() {
        String str = "Kotlin";
        System.out.println(hello(str, "Hi")); // 调用静态方法，传入接收者 str
    }

    public static void main(String[] args) {
        main();
    }
}
```

##### 3. 关键字节码指令（简化版）
重点看 `main` 方法调用扩展函数的字节码：
```bytecode
// main 方法中调用 str.hello("Hi") 的字节码
0: ldc           #9          // 加载字符串常量 "Kotlin"（接收者 str）
2: astore_0                   // 存储到局部变量 0（str）
3: aload_0                    // 压入接收者 str（第一个参数）
4: ldc           #11         // 压入参数 "Hi"（第二个参数）
6: invokestatic  #17         // 调用静态方法：StringExtensionsKt.hello(Ljava/lang/String;Ljava/lang/String;)Ljava/lang/String;
9: astore_1                   // 存储返回值
10: getstatic    #23         // 加载 System.out
13: aload_1                    // 压入返回值
14: invokevirtual #29         // 调用 println 方法
```
- 核心指令：`invokestatic` → 直接调用静态方法，而非目标类 `String` 的实例方法（如 `invokevirtual`）；
- 接收者 `str` 被作为**第一个参数**传入静态方法，这就是 `this` 在扩展函数中的本质。


#### 示例 2：可空接收者的扩展函数
如果扩展函数的接收者是可空类型（如 `String?`），字节码层面会移除非空检查：
```kotlin
// 可空接收者的扩展函数
fun String?.safeHello(): String {
    return this?.let { "Hello $it" } ?: "Hello null"
}
```

反编译后的 Java 代码（核心部分）：
```java
public static final String safeHello(String $this$safeHello) {
    // 无 Intrinsics.checkNotNullParameter 检查（接收者可空）
    return $this$safeHello != null ? ("Hello " + $this$safeHello) : "Hello null";
}
```
字节码层面不会额外生成 null 检查指令，完全由开发者在函数内部处理 `this == null` 的情况。


#### 示例 3：扩展属性（本质是扩展方法）
Kotlin 扩展属性也遵循同样逻辑，编译为静态的 `getter/setter` 方法（无字段，仅方法）：
```kotlin
// 给 String 扩展一个只读属性 lengthDouble
val String.lengthDouble: Double
    get() = this.length.toDouble()
```

反编译后的 Java 代码：
```java
public static final double getLengthDouble(String $this$lengthDouble) {
    Intrinsics.checkNotNullParameter($this$lengthDouble, "$this$lengthDouble");
    return (double) $this$lengthDouble.length();
}
```
调用时 `str.lengthDouble` 会被编译为 `StringExtensionsKt.getLengthDouble(str)`（静态方法调用）。


### 三、特殊场景的字节码处理
#### 1. 类内部声明的扩展函数
如果扩展函数声明在某个类内部（非顶层），会编译为该类的静态方法（若为 `inner` 扩展则为非静态，需依赖外部类实例）：
```kotlin
class MyClass {
    // 类内部的扩展函数
    fun String.innerHello(): String {
        return "Inner: $this"
    }
}
```

反编译后的 Java 代码：
```java
public final class MyClass {
    // 静态方法：接收者 String 作为第一个参数
    public final String innerHello(String $this$innerHello) {
        Intrinsics.checkNotNullParameter($this$innerHello, "$this$innerHello");
        return "Inner: " + $this$innerHello;
    }
}

// 调用时
MyClass myClass = new MyClass();
myClass.innerHello("Test"); // 本质还是静态方法调用（Java 视角）
```

#### 2. 泛型扩展函数
泛型扩展函数编译为带泛型参数的静态方法，字节码层面保留泛型信息（通过 `Signature` 注解）：
```kotlin
fun <T> List<T>.printAll() {
    this.forEach { println(it) }
}
```

反编译后的 Java 代码（核心）：
```java
// 泛型静态方法，T 为类型参数
public static final <T> void printAll(List<T> $this$printAll) {
    Intrinsics.checkNotNullParameter($this$printAll, "$this$printAll");
    Iterable $this$forEach$iv = (Iterable)$this$printAll;
    Iterator var2 = $this$forEach$iv.iterator();
    // ... 遍历逻辑
}
```

#### 3. 与目标类成员函数冲突
如果扩展函数名与目标类的成员函数名相同，**成员函数优先调用**（字节码层面调用指令不同）：
```kotlin
fun String.length(): Int { // 扩展函数与 String 原生 length() 同名
    return this.length * 2
}

fun main() {
    val str = "abc"
    println(str.length()) // 调用原生成员函数（输出 3），而非扩展函数
}
```
- 字节码层面：`str.length()` 会编译为 `invokevirtual java/lang/String.length()I`（调用成员方法），而非 `invokestatic`（扩展函数）；
- 原因：Kotlin 编译器在解析时，优先匹配目标类的成员方法，再匹配扩展函数。


### 四、核心总结（字节码层面）
1. **无侵入性**：目标类的字节码完全不变，扩展函数不修改目标类的字段、方法列表，仅生成独立的静态工具方法；
2. **语法糖本质**：扩展函数 = 静态方法 + 接收者作为第一个参数 + `this` 语法糖；
3. **调用逻辑**：`接收者.扩展函数(参数)` → 编译为 `工具类.静态方法(接收者, 参数)`，字节码指令为 `invokestatic`；
4. **空安全**：非空接收者会生成 `Intrinsics.checkNotNullParameter` 字节码检查，可空接收者则不检查；
5. **扩展属性**：无字段，仅编译为 `getXXX()`/`setXXX()` 静态方法。


### 关键区别：扩展函数 vs 成员函数（字节码层面）
| 特性                | 扩展函数                          | 成员函数                          |
|---------------------|-----------------------------------|-----------------------------------|
| 字节码载体          | 独立工具类（XXXKt）或所在类       | 目标类本身                        |
| 调用指令            | `invokestatic`（静态调用）        | `invokevirtual`/`invokeinterface`（实例调用） |
| 接收者处理          | 作为第一个参数传入                | 隐含为 `this`（通过 `aload_0` 加载） |
| 目标类依赖          | 不依赖目标类源码（可扩展第三方类）| 必须在目标类内部声明              |
| 继承覆盖            | 无法被目标类子类覆盖              | 可被子类重写（`open` 修饰）       |


综上，Kotlin 扩展函数的底层实现是「静态方法 + 语法糖包装」，既实现了「给任意类加方法」的灵活语法，又避免了修改原类字节码的侵入性，完全兼容 Java 字节码规范。